box21_api/__init__.py
box21_api/_modidx.py
box21_api/annotation.py
box21_api/annotation_stat.py
box21_api/asset.py
box21_api/box21_api.py
box21_api/export.py
box21_api/filters.py
box21_api/job.py
box21_api/label.py
box21_api-0.0.17.dist-info/LICENSE
box21_api-0.0.17.dist-info/METADATA
box21_api-0.0.17.dist-info/WHEEL
box21_api-0.0.17.dist-info/entry_points.txt
box21_api-0.0.17.dist-info/top_level.txt
box21_api-0.0.17.dist-info/RECORD
