Metadata-Version: 2.1
Name: box21_api
Version: 0.0.17
Summary: Api for Box21.ai
Home-page: https://github.com/ramonhollands/box21_api
Author: Ramon
Author-email: ramonhollands@gmail.com
License: Apache Software License 2.0
Keywords: nbdev jupyter notebook python
Classifier: Development Status :: 4 - Beta
Classifier: Intended Audience :: Developers
Classifier: Natural Language :: English
Classifier: Programming Language :: Python :: 3.7
Classifier: Programming Language :: Python :: 3.8
Classifier: Programming Language :: Python :: 3.9
Classifier: Programming Language :: Python :: 3.10
Classifier: License :: OSI Approved :: Apache Software License
Requires-Python: >=3.7
License-File: LICENSE
Requires-Dist: fastcore
Requires-Dist: pandas
Requires-Dist: pillow
Requires-Dist: requests
Requires-Dist: load-dotenv
Provides-Extra: dev
